{
    "@id": "",
    "@title": "",
    "@titleTextStyle": {
        "@color": "",
        "@fontName": "",
        "@fontSize": "",
        "@bold": "",
        "@italic": ""
    },
    "@legendPosition": "bottom || left || right || in || top || none",
    "@fontSize": "",
    "@fontName": "",
    "@chartWidth": 700,
    "@chartHeight": 400,
    "@colors": [],
    "@enableInteractivity": "true (default) || false",
    "@forceIFrame": "true || false(default)",
    "@bubble": {
        "@color": "",
        "@fontName": "",
        "@fontSize": "",
        "@bold": "",
        "@italic": ""
    },
    "@hAxis": {
        "@title": "",
        "@color": "",
        "@fontName": "",
        "@fontSize": "",
        "@bold": "",
        "@italic": "",
        "@maxValue": "",
        "@minValue": "",
        "@gridlineCount": "",
        "@gridlineColor": "",
        "@ticks": []
    },
    "@vAxis": {
        "@title": "",
        "@color": "",
        "@fontName": "",
        "@fontSize": "",
        "@bold": "",
        "@italic": "",
        "@maxValue": "",
        "@minValue": "",
        "@gridlineCount": "",
        "@gridlineColor": "",
        "@ticks": []
    },
    "@animateChart": "true || false(default)",
    "@animationDuration": "2000ms",
    "@transitionStyle": "linear || in || out || inAndOut",
    ">": [
        ["ID", "Life Expectancy", "Fertility Rate", "Region", "Population"],
        ["CAN", 80.66, 1.67, "North America", 33739900],
        ["DEU", 79.84, 1.36, "Europe", 81902307],
        ["DNK", 78.6, 1.84, "Europe", 5523095],
        ["EGY", 72.73, 2.78, "Middle East", 79716203],
        ["GBR", 80.05, 2, "Europe", 61801570],
        ["IRN", 72.49, 1.7, "Middle East", 73137148],
        ["IRQ", 68.09, 4.77, "Middle East", 31090763],
        ["ISR", 81.55, 2.96, "Middle East", 7485600],
        ["RUS", 68.6, 1.54, "Europe", 141850000],
        ["USA", 78.09, 2.05, "North America", 307007000]
    ]
}